{"name":"EditorFileSystemDirectory","parent":"Object","comment":"A directory for the resource filesystem.","des":"","const":[],"enums":[],"props":[],"setters":[],"getters":[],"methods":[{"name":"find_dir_index","fun":"const int find_dir_index(String name)"},{"name":"find_file_index","fun":"const int find_file_index(String name)"},{"name":"get_file","fun":"const String get_file(int idx)"},{"name":"get_file_count","fun":"const int get_file_count()"},{"name":"get_file_import_is_valid","fun":"const bool get_file_import_is_valid(int idx)"},{"name":"get_file_path","fun":"const String get_file_path(int idx)"},{"name":"get_file_script_class_extends","fun":"const String get_file_script_class_extends(int idx)"},{"name":"get_file_script_class_name","fun":"const String get_file_script_class_name(int idx)"},{"name":"get_file_type","fun":"const String get_file_type(int idx)"},{"name":"get_name","fun":" String get_name()"},{"name":"get_parent","fun":" EditorFileSystemDirectory get_parent()"},{"name":"get_path","fun":"const String get_path()"},{"name":"get_subdir","fun":" EditorFileSystemDirectory get_subdir(int idx)"},{"name":"get_subdir_count","fun":"const int get_subdir_count()"}],"signals":[]}