{"name":"EditorVCSInterface","parent":"Object","comment":"Version Control System (VCS) interface which reads and writes to the local VCS in use.","des":"","const":[],"enums":[],"props":[],"setters":[],"getters":[],"methods":[{"name":"commit","fun":" void commit(String msg)"},{"name":"get_file_diff","fun":" Array get_file_diff(String file_path)"},{"name":"get_modified_files_data","fun":" Dictionary get_modified_files_data()"},{"name":"get_project_name","fun":" String get_project_name()"},{"name":"get_vcs_name","fun":" String get_vcs_name()"},{"name":"initialize","fun":" bool initialize(String project_root_path)"},{"name":"is_addon_ready","fun":" bool is_addon_ready()"},{"name":"is_vcs_initialized","fun":" bool is_vcs_initialized()"},{"name":"shut_down","fun":" bool shut_down()"},{"name":"stage_file","fun":" void stage_file(String file_path)"},{"name":"unstage_file","fun":" void unstage_file(String file_path)"}],"signals":[]}