{"name":"HeightMapShape","parent":"Shape","comment":"Height map shape for 3D physics.","des":"","const":[],"enums":[],"props":[{"name":"map_data","prop":"PoolRealArray map_data  = PoolRealArray( 0, 0, 0, 0 )","setget":"true"},{"name":"map_depth","prop":"int map_depth  = 2","setget":"true"},{"name":"map_width","prop":"int map_width  = 2","setget":"true"}],"setters":["set_map_data(PoolRealArray value)","set_map_depth(int value)","set_map_width(int value)"],"getters":["PoolRealArray get_map_data()","int get_map_depth()","int get_map_width()"],"methods":[],"signals":[]}