{"name":"Shape2D","parent":"Resource","comment":"Base class for all 2D shapes.","des":"","const":[],"enums":[],"props":[{"name":"custom_solver_bias","prop":"float custom_solver_bias  = 0.0","setget":"true"}],"setters":["set_custom_solver_bias(float value)"],"getters":["float get_custom_solver_bias()"],"methods":[{"name":"collide","fun":" bool collide(Transform2D local_xform,Shape2D with_shape,Transform2D shape_xform)"},{"name":"collide_and_get_contacts","fun":" Array collide_and_get_contacts(Transform2D local_xform,Shape2D with_shape,Transform2D shape_xform)"},{"name":"collide_with_motion","fun":" bool collide_with_motion(Transform2D local_xform,Vector2 local_motion,Shape2D with_shape,Transform2D shape_xform,Vector2 shape_motion)"},{"name":"collide_with_motion_and_get_contacts","fun":" Array collide_with_motion_and_get_contacts(Transform2D local_xform,Vector2 local_motion,Shape2D with_shape,Transform2D shape_xform,Vector2 shape_motion)"},{"name":"draw","fun":" void draw(RID canvas_item,Color color)"}],"signals":[]}